first_library/__init__.py
first_library/functions.py
first_library2003-0.1.0.dist-info/METADATA
first_library2003-0.1.0.dist-info/WHEEL
first_library2003-0.1.0.dist-info/top_level.txt
first_library2003-0.1.0.dist-info/RECORD
