Metadata-Version: 2.1
Name: first-library2003
Version: 0.1.0
Summary: My first Python library
Home-page: UNKNOWN
Author: Me
License: UNKNOWN
Platform: UNKNOWN
